airless/config.py
airless/dto/__init__.py
airless/dto/pubsub_to_bq.py
airless/hook/__init__.py
airless/hook/base.py
airless/hook/file/__init__.py
airless/hook/file/file.py
airless/hook/file/ftp.py
airless/hook/google/__init__.py
airless/hook/google/bigquery.py
airless/hook/google/pubsub.py
airless/hook/google/secret_manager.py
airless/hook/google/storage.py
airless/hook/notification/__init__.py
airless/hook/notification/email.py
airless/hook/notification/slack.py
airless/operator/__init__.py
airless/operator/base.py
airless/operator/delay.py
airless/operator/error.py
airless/operator/redirect.py
airless/operator/file/__init__.py
airless/operator/file/file.py
airless/operator/file/ftp.py
airless/operator/google/__init__.py
airless/operator/google/bigquery.py
airless/operator/google/storage.py
airless/operator/notification/__init__.py
airless/operator/notification/email.py
airless/operator/notification/slack.py
airless/service/__init__.py
airless/service/base.py
airless/service/captcha.py
airless/utils/__init__.py
airless/utils/decorators.py
samples/example/main.py
tests/__init__.py
tests/operator/__init__.py
tests/operator/google/__init__.py
airless-0.0.73.dist-info/LICENSE
airless-0.0.73.dist-info/METADATA
airless-0.0.73.dist-info/WHEEL
airless-0.0.73.dist-info/top_level.txt
airless-0.0.73.dist-info/RECORD
