Metadata-Version: 2.1
Name: airless
Version: 0.0.73
Summary: Airless is a package that aims to build a serverless and lightweight orchestration platform, creating workflows of multiple tasks being executed on FaaS platform
Project-URL: Homepage, https://github.com/astercapital/airless
Project-URL: Bug Tracker, https://github.com/astercapital/airless/issues
License-File: LICENSE
Requires-Dist: google-cloud-storage==2.17.0
Requires-Dist: google-cloud-pubsub==2.13.11
Requires-Dist: google-cloud-bigquery==3.25.0
Requires-Dist: google-cloud-secret-manager==2.12.6
Requires-Dist: unidecode==1.3.4
Requires-Dist: ndjson==0.3.1
